sktda/__init__.py
sktda/_version.py
scikit_tda-1.1.1.dist-info/LICENSE
scikit_tda-1.1.1.dist-info/METADATA
scikit_tda-1.1.1.dist-info/WHEEL
scikit_tda-1.1.1.dist-info/top_level.txt
scikit_tda-1.1.1.dist-info/RECORD
