Metadata-Version: 2.1
Name: scikit-tda
Version: 1.1.1
Summary: Topological Data Analysis for humans
Home-page: https://github.com/scikit-tda/scikit-tda
Author: Nathaniel Saul, Chris Tralie
Author-email: nathaniel.saul@wsu.edu, chris.tralie@gmail.com
License: MIT
Keywords: topology data analysis,algebraic topology,unsupervised learning,persistent homology,persistence images,persistence diagrams,uniform manifold approximation and projection,sheaf theory,mapper,data visualization
Classifier: Development Status :: 3 - Alpha
Classifier: Intended Audience :: Science/Research
Classifier: Intended Audience :: Education
Classifier: Intended Audience :: Financial and Insurance Industry
Classifier: Intended Audience :: Healthcare Industry
Classifier: Topic :: Scientific/Engineering :: Information Analysis
Classifier: Topic :: Scientific/Engineering :: Mathematics
Classifier: License :: OSI Approved :: MIT License
Classifier: Programming Language :: Python :: 3
Classifier: Programming Language :: Python :: 3.4
Classifier: Programming Language :: Python :: 3.5
Classifier: Programming Language :: Python :: 3.6
Classifier: Programming Language :: Python :: 3.7
Classifier: Programming Language :: Python :: 3.8
Requires-Python: >3.3
License-File: LICENSE
Requires-Dist: numpy
Requires-Dist: scipy
Requires-Dist: scikit-learn
Requires-Dist: matplotlib
Requires-Dist: Cython
Requires-Dist: ripser
Requires-Dist: persim
Requires-Dist: pillow
Requires-Dist: kmapper
Requires-Dist: tadasets
Provides-Extra: testing
Requires-Dist: pytest; extra == "testing"
Provides-Extra: docs
Requires-Dist: sktda_docs_config; extra == "docs"
Requires-Dist: pyyaml; extra == "docs"
